<?xml version="1.0" encoding="utf-16"?>
<Level width="2">
  <Camera x="0" y="-1" minWidth="25" maxWidth="35" />
  <Score highScore="0" />
  <Birds>
    <Bird type="BirdRed"/>
  </Birds>
  <Slingshot x="-12.0" y="-2.5" />

  <GameObjects>
    <Pig type="BasicSmall" material="" x="-0.5167" y="0.2295" rotation="0.3056" />
    <Platform type="Platform" material="" x="-1.4673" y="-0.1537" rotation="0.0" scaleX="4.7346" scaleY="0.5" />
    <Platform type="Platform" material="" x="-0.1142" y="0.6964" rotation="90.0" scaleX="3.1031" scaleY="0.5" />
    <Platform type="Platform" material="" x="-1.9612" y="1.5263" rotation="0.0" scaleX="1.0" scaleY="0.5" />
    <Platform type="Platform" material="" x="-1.8142" y="0.5364" rotation="90.0" scaleX="2.5976" scaleY="0.5" />
    <ExternalAgent type="novel_object_37_1_1" material="" x="4.0511" y="-1.1629" rotation="0.0" />
    <Block type="RectFat" material="wood" x="2.0158" y="-1.1575" rotation="0.0" />
    <Block type="RectFat" material="wood" x="7.0158" y="-1.1575" rotation="0.0" />
    <Block type="RectBig" material="ice" x="8.7979" y="-3.39" rotation="0" />
  </GameObjects>
</Level>
