<?xml version="1.0" encoding="utf-16"?>
<Level width="2">
  <Camera x="0" y="-1" minWidth="25" maxWidth="35" />
  <Score highScore="0" />
  <Birds>
    <Bird type="BirdBlue"/>
  </Birds>
  <Slingshot x="-12.0" y="-2.5" />
  <GameObjects>
    <Pig type="BasicSmall" material="" x="0.0659" y="-0.1669" rotation="0.5998" />
    <Block type="RectMedium" material="stone" x="-0.566" y="-0.2661" rotation="0.0" />
    <Block type="RectMedium" material="stone" x="-2.2761" y="-0.2661" rotation="0.0" />
    <Platform type="Platform" material="" x="-1.315" y="-0.5511" rotation="0.0" scaleX="6.0982" scaleY="0.5" />
    <Platform type="Platform" material="" x="0.474" y="0.299" rotation="90.0" scaleX="3.1031" scaleY="0.5" />
    <Platform type="Platform" material="" x="-1.3731" y="1.1289" rotation="0.0" scaleX="1.0" scaleY="0.5" />
    <Platform type="Platform" material="" x="-1.226" y="0.489" rotation="90.0" scaleX="1.5038" scaleY="0.5" />
    <Block type="RectBig" material="wood" x="-5.8154" y="-3.39" rotation="0" />
    <Block type="RectSmall" material="stone" x="-9.087" y="-3.39" rotation="0" />
    <Block type="RectBig" material="ice" x="0.2249" y="-3.39" rotation="0" />
    <Block type="TriangleHole" material="stone" x="3.4427" y="-3.09" rotation="0" />
    <Block type="SquareSmall" material="wood" x="7.4925" y="-3.285" rotation="0" />
  </GameObjects>
</Level>
