<?xml version="1.0" encoding="utf-16"?>
<Level width="2">
  <Camera x="0" y="-1" minWidth="25" maxWidth="35" />
  <Score highScore="0" />
  <Birds>
    <Bird type="BirdRed"/>
  </Birds>
  <Slingshot x="-12.0" y="-2.5" />
  <GameObjects>
    <Pig type="BasicSmall" material="" x="-5.037" y="-0.6723" rotation="0.3056" />
    <Platform type="Platform" material="" x="-5.9875" y="-1.0555" rotation="0.0" scaleX="4.7346" scaleY="0.5" />
    <Platform type="Platform" material="" x="-4.6344" y="-0.2054" rotation="90.0" scaleX="3.1031" scaleY="0.5" />
    <ExternalAgent type="novel_object_36_2_1" material="" x="-6.0044" y="1.2646" rotation="0.0" scaleX="1.0" scaleY="1.0" />
    <Block type="SquareHole" material="ice" x="3.6228" y="-3.08" rotation="0" />
    <Block type="TriangleHole" material="wood" x="6.8032" y="-3.09" rotation="0" />
    <Block type="RectBig" material="ice" x="-3.3462" y="-3.39" rotation="0" />
    <Block type="RectSmall" material="wood" x="-6.7648" y="-3.39" rotation="0" />
    <ExternalAgent type="Wizard" material="" x="-1.9175" y="2.7603" rotation="0" />
  </GameObjects>
</Level>
