<?xml version="1.0" encoding="utf-16"?>
<Level width="2">
  <Camera x="0" y="-1" minWidth="25" maxWidth="35" />
  <Score highScore="0" />
  <Birds>
    <Bird type="BirdRed"/>
  </Birds>
  <Slingshot x="-12.0" y="-2.5" />
  <GameObjects>
    <Pig type="BasicSmall" material="" x="-4.3736" y="-1.663" rotation="0.5998" />
    <Platform type="Platform" material="" x="-4.8765" y="-2.0443" rotation="0.0" scaleX="4.7346" scaleY="0.5" />
    <Platform type="Platform" material="" x="-3.5234" y="-1.1942" rotation="90.0" scaleX="3.1031" scaleY="0.5" />
    <Platform type="Platform" material="" x="-4.5394" y="-0.3643" rotation="0.0" scaleX="3.5953" scaleY="0.5" />
    <Novelty type="novel_object_36_1_1" material="" x="-11.3934" y="-2.7242" rotation="0.0" scaleX="1.0" scaleY="1.0" />
    <Block type="Circle" material="ice" x="2.4724" y="-3.1" rotation="0" />
    <Block type="TriangleHole" material="stone" x="6.2441" y="-3.09" rotation="0" />
    <Block type="Circle" material="stone" x="-3.3977" y="-3.1" rotation="0" />
    <ExternalAgent type="Magician" material="" x="-0.7706" y="-2.8293" rotation="0" />
  </GameObjects>
</Level>
