<?xml version="1.0" encoding="utf-16"?>
<Level width="2">
  <Camera x="0" y="-1" minWidth="25" maxWidth="35" />
  <Score highScore="0" />
  <Birds>
    <Bird type="BirdRed"/>
  </Birds>
  <Slingshot x="-12.0" y="-2.5" />
  <GameObjects>
    <Pig type="BasicSmall" material="" x="-5.1196" y="-0.3485" rotation="1.2754" />
    <Platform type="Platform" material="" x="-5.1196" y="-0.6945" rotation="0.0" scaleX="4.0" scaleY="0.5" />
    <Block type="RectMedium" material="ice" x="-5.1196" y="-2.6345" rotation="0.0" />
    <Platform type="Platform" material="" x="-6.2426" y="-0.2345" rotation="90.0" scaleX="2.0" scaleY="0.5" />
    <Platform type="Platform" material="" x="-3.9966" y="-0.2285" rotation="90.0" scaleX="2.0" scaleY="0.5" />
    <Platform type="Platform" material="" x="-5.1196" y="-2.9245" rotation="0.0" scaleX="2.0" scaleY="0.5" />
    <Block type="CircleSmall" material="ice" x="-9.5091" y="-3.275" rotation="0" />
    <Block type="CircleSmall" material="wood" x="8.2942" y="-3.275" rotation="0" />
    <Block type="Triangle" material="ice" x="-3.1695" y="-3.09" rotation="0" />
    <Block type="Circle" material="stone" x="-7.7471" y="-3.1" rotation="0" />
    <Block type="Circle" material="wood" x="3.8768" y="-3.1" rotation="0" />
  </GameObjects>
</Level>
