<?xml version="1.0" encoding="utf-16"?>
<Level width="2">
  <Camera x="0" y="-1" minWidth="25" maxWidth="35" />
  <Score highScore="0" />
  <Birds>
    <Bird type="BirdRed"/>
  </Birds>
  <Slingshot x="-12.0" y="-2.5" />
  <GameObjects>
    <Pig type="BasicSmall" material="" x="-2.9125" y="0.4632" rotation="1.2754" />
    <Platform type="Platform" material="" x="-2.9125" y="0.1172" rotation="0.0" scaleX="4.0" scaleY="0.5" />
    <Block type="RectMedium" material="ice" x="-2.9125" y="-1.8228" rotation="0.0" />
    <Platform type="Platform" material="" x="-4.0355" y="0.5772" rotation="90.0" scaleX="2.0" scaleY="0.5" />
    <Platform type="Platform" material="" x="-1.7895" y="0.5832" rotation="90.0" scaleX="2.0" scaleY="0.5" />
    <Platform type="Platform" material="" x="-2.9125" y="-2.1128" rotation="0.0" scaleX="2.0" scaleY="0.5" />
    <Block type="CircleSmall" material="ice" x="-8.6913" y="-3.275" rotation="0" />
    <Block type="RectMedium" material="ice" x="3.6444" y="-3.39" rotation="0" />
    <Platform type="Platform" material="" x="-6.8819" y="-3.18" rotation="0" scaleX="1.0" scaleY="1.0" />
    <Block type="RectSmall" material="stone" x="-5.4637" y="-3.39" rotation="0" />
  </GameObjects>
</Level>
