<?xml version="1.0" encoding="utf-16"?>
<Level width="2">
  <Camera x="0" y="-1" minWidth="25" maxWidth="35" />
  <Score highScore="0" />
  <Birds>
    <Bird type="BirdRed"/>
    <Bird type="BirdRed"/>
  </Birds>
  <Slingshot x="-12.0" y="-2.5" />
  <GameObjects>
    <Pig type="BasicSmall" material="" x="-4.9815" y="-0.4302" rotation="0.0" />
    <Pig type="BasicSmall" material="" x="-4.9815" y="-3.3055" rotation="0.0" />
    <Platform type="Platform" material="" x="-6.3153" y="-0.8116" rotation="0.0" scaleX="7.2436" scaleY="0.5" />
    <Platform type="Platform" material="" x="-4.9853" y="1.8685" rotation="0.0" scaleX="3.1733" scaleY="0.5" />
    <Platform type="Platform" material="" x="-4.1313" y="0.5085" rotation="90.0" scaleX="4.1031" scaleY="0.5" />
    <Platform type="Platform" material="" x="-8.2013" y="1.8685" rotation="0.0" scaleX="1.2332" scaleY="0.5" />
    <Block type="novel_object_38_2_1" material="stone" x="-6.8913" y="2.1534" rotation="0.0" />
    <Block type="SquareHole" material="stone" x="-6.4683" y="3.56" rotation="0.0" />
    <Block type="SquareHole" material="stone" x="-6.4683" y="2.6999" rotation="0.0" />
    <Block type="SquareHole" material="stone" x="-6.4683" y="4.4185" rotation="0.0" />
    <Block type="SquareHole" material="stone" x="-7.3413" y="3.56" rotation="0.0" />
    <Block type="SquareHole" material="stone" x="-7.3413" y="2.6999" rotation="0.0" />
    <Block type="SquareHole" material="stone" x="-7.3413" y="4.4185" rotation="0.0" />
    <Block type="RectBig" material="wood" x="-7.5391" y="-3.39" rotation="0" />
    <Block type="SquareHole" material="ice" x="4.3638" y="-3.08" rotation="0" />
    <ExternalAgent type="Butterfly" material="" x="-9.9173" y="-2.84" rotation="0" />
  </GameObjects>
</Level>
