<?xml version="1.0" encoding="utf-16"?>
<Level width="2">
  <Camera x="0" y="-1" minWidth="25" maxWidth="35" />
  <Score highScore="0" />
  <Birds>
    <Bird type="BirdRed"/>
    <Bird type="BirdRed"/>
  </Birds>
  <Slingshot x="-12.0" y="-2.5" />
  <GameObjects>
    <Pig type="BasicSmall" material="" x="-6.5842" y="-0.7832" rotation="0.3056" />
    <Pig type="novel_object_1014" material="" x="1.3492" y="-3.21" rotation="0" />
    <Platform type="Platform" material="" x="-7.5348" y="-1.1664" rotation="0.0" scaleX="4.7346" scaleY="0.5" />
    <Platform type="Platform" material="" x="-6.1817" y="-0.3163" rotation="90.0" scaleX="3.1031" scaleY="0.5" />
    <Platform type="Platform" material="" x="-8.0287" y="0.5136" rotation="0.0" scaleX="1.0" scaleY="0.5" />
    <Platform type="Platform" material="" x="-7.8817" y="-0.4763" rotation="90.0" scaleX="2.5976" scaleY="0.5" />
    <Block type="Circle" material="stone" x="-2.0786" y="-3.1" rotation="0" />
  </GameObjects>
</Level>
