<?xml version="1.0" encoding="utf-16"?>
<Level width="2">
  <Camera x="0" y="-1" minWidth="25" maxWidth="35" />
  <Score highScore="0" />
  <Birds>
    <Bird type="BirdRed"/>
    <Bird type="BirdRed"/>
  </Birds>
  <Slingshot x="-12.0" y="-2.5" />
  <GameObjects>
    <Pig type="BasicSmall" material="" x="-1.4455" y="-0.5657" rotation="0.3056" />
    <Pig type="novel_object_1014" material="" x="-9.2477" y="-3.21" rotation="0" />
    <Platform type="Platform" material="" x="-2.396" y="-0.9489" rotation="0.0" scaleX="4.7346" scaleY="0.5" />
    <Platform type="Platform" material="" x="-1.0429" y="-0.0988" rotation="90.0" scaleX="3.1031" scaleY="0.5" />
    <Platform type="Platform" material="" x="-2.8899" y="0.7311" rotation="0.0" scaleX="1.0" scaleY="0.5" />
    <Platform type="Platform" material="" x="-2.7429" y="-0.2588" rotation="90.0" scaleX="2.5976" scaleY="0.5" />
    <Block type="SquareTiny" material="stone" x="-3.2447" y="-3.39" rotation="0" />
    <Block type="RectMedium" material="ice" x="6.7315" y="-3.39" rotation="0" />
    <Block type="Circle" material="wood" x="-1.8035" y="-3.1" rotation="0" />
    <Block type="RectSmall" material="wood" x="-5.6225" y="-3.39" rotation="0" />
  </GameObjects>
</Level>
