<?xml version="1.0" encoding="utf-16"?>
<Level width="2">
  <Camera x="0" y="-1" minWidth="25" maxWidth="35" />
  <Score highScore="0" />
  <Birds>
    <Bird type="BirdRed"/>
    <Bird type="BirdRed"/>
  </Birds>
  <Slingshot x="-12.0" y="-2.5" />
  <GameObjects>
    <Pig type="BasicSmall" material="" x="-5.8995" y="-0.4853" rotation="0.0" />
    <Pig type="BasicSmall" material="" x="-5.8995" y="-3.3606" rotation="0.0" />
    <Platform type="Platform" material="" x="-7.2333" y="-0.8667" rotation="0.0" scaleX="7.2436" scaleY="0.5" />
    <Platform type="Platform" material="" x="-5.9033" y="1.8134" rotation="0.0" scaleX="3.1733" scaleY="0.5" />
    <Platform type="Platform" material="" x="-5.0493" y="0.4534" rotation="90.0" scaleX="4.1031" scaleY="0.5" />
    <Platform type="Platform" material="" x="-9.1193" y="1.8134" rotation="0.0" scaleX="1.2332" scaleY="0.5" />
    <Block type="novel_object_38_2_1" material="stone" x="-7.8093" y="2.0983" rotation="0.0" />
    <Block type="SquareHole" material="stone" x="-7.3863" y="3.5049" rotation="0.0" />
    <Block type="SquareHole" material="stone" x="-7.3863" y="2.6448" rotation="0.0" />
    <Block type="SquareHole" material="stone" x="-7.3863" y="4.3634" rotation="0.0" />
    <Block type="SquareHole" material="stone" x="-8.2593" y="3.5049" rotation="0.0" />
    <Block type="SquareHole" material="stone" x="-8.2593" y="2.6448" rotation="0.0" />
    <Block type="SquareHole" material="stone" x="-8.2593" y="4.3634" rotation="0.0" />
    <Block type="RectMedium" material="ice" x="6.8867" y="-3.39" rotation="0" />
    <Block type="RectFat" material="stone" x="2.1259" y="-3.285" rotation="0" />
    <Block type="TriangleHole" material="ice" x="-2.7152" y="-3.09" rotation="0" />
    <ExternalAgent type="Worm" material="" x="-7.2333" y="-0.8667" rotation="0" />
  </GameObjects>
</Level>
