<?xml version="1.0" encoding="utf-16"?>
<Level width="2">
  <Camera x="0" y="-1" minWidth="25" maxWidth="35" />
  <Score highScore="0" />
  <Birds>
    <Bird type="BirdRed"/>
    <Bird type="BirdRed"/>
  </Birds>
  <Slingshot x="-12.0" y="-2.5" />
  <GameObjects>
    <Pig type="BasicSmall" material="" x="-4.1602" y="-0.4439" rotation="0.0" />
    <Pig type="BasicSmall" material="" x="-4.1602" y="-3.3191" rotation="0.0" />
    <Platform type="Platform" material="" x="-5.494" y="-0.8252" rotation="0.0" scaleX="7.2436" scaleY="0.5" />
    <Platform type="Platform" material="" x="-4.164" y="1.8549" rotation="0.0" scaleX="3.1733" scaleY="0.5" />
    <Platform type="Platform" material="" x="-3.31" y="0.4949" rotation="90.0" scaleX="4.1031" scaleY="0.5" />
    <Platform type="Platform" material="" x="-7.38" y="1.8549" rotation="0.0" scaleX="1.2332" scaleY="0.5" />
    <Block type="novel_object_38_2_1" material="stone" x="-6.07" y="2.1398" rotation="0.0" />
    <Block type="SquareHole" material="stone" x="-5.647" y="3.5464" rotation="0.0" />
    <Block type="SquareHole" material="stone" x="-5.647" y="2.6862" rotation="0.0" />
    <Block type="SquareHole" material="stone" x="-5.647" y="4.4049" rotation="0.0" />
    <Block type="SquareHole" material="stone" x="-6.52" y="3.5464" rotation="0.0" />
    <Block type="SquareHole" material="stone" x="-6.52" y="2.6862" rotation="0.0" />
    <Block type="SquareHole" material="stone" x="-6.52" y="4.4049" rotation="0.0" />
    <Block type="SquareTiny" material="ice" x="3.0152" y="-3.39" rotation="0" />
    <Block type="SquareTiny" material="stone" x="0.1678" y="-3.39" rotation="0" />
    <Platform type="Platform" material="" x="8.3524" y="-3.18" rotation="0" scaleX="1.0" scaleY="1.0" />
    <Block type="CircleSmall" material="ice" x="-8.6939" y="-3.275" rotation="0" />
    <ExternalAgent type="Magician" material="" x="5.7478" y="-2.8293" rotation="0" />
  </GameObjects>
</Level>
