<?xml version="1.0" encoding="utf-16"?>
<Level width="2">
  <Camera x="0" y="-1" minWidth="25" maxWidth="35" />
  <Score highScore="0" />
  <Birds>
    <Bird type="BirdRed"/>
    <Bird type="BirdRed"/>
  </Birds>
  <Slingshot x="-12.0" y="-2.5" />
  <GameObjects>
    <Pig type="BasicSmall" material="" x="1.3292" y="0.7684" rotation="0.9321" />
    <Pig type="BasicSmall" material="" x="-0.5461" y="0.7667" rotation="359.6748" />
    <Platform type="Platform" material="" x="-0.1071" y="0.3827" rotation="0.0" scaleX="6.2566" scaleY="0.5" />
    <Platform type="Platform" material="" x="-1.9581" y="0.8637" rotation="90.0" scaleX="2.0" scaleY="0.5" />
    <Platform type="Platform" material="" x="1.7329" y="0.8734" rotation="90.0" scaleX="1.979" scaleY="0.5" />
    <Platform type="Platform" material="" x="-0.1441" y="1.0127" rotation="90.0" scaleX="1.5158" scaleY="0.5" />
    <Block type="SquareSmall" material="ice" x="7.2131" y="-3.285" rotation="0" />
    <Block type="TriangleHole" material="wood" x="-8.2166" y="-3.09" rotation="0" />
    <Block type="RectMedium" material="stone" x="1.0589" y="-3.39" rotation="0" />
    <ExternalAgent type="Wizard" material="" x="-4.6701" y="-2.2042" rotation="0" />
  </GameObjects>
</Level>
