<?xml version="1.0" encoding="utf-16"?>
<Level width="2">
  <Camera x="0" y="-1" minWidth="25" maxWidth="35" />
  <Score highScore="0" />
  <Birds>
    <Bird type="BirdRed"/>
  </Birds>
  <Slingshot x="-12.0" y="-2.5" />
  <GameObjects>
    <Pig type="BasicSmall" material="" x="-1.2992" y="0.101" rotation="0.5998" />
    <Platform type="Platform" material="" x="-1.8021" y="-0.2803" rotation="0.0" scaleX="4.7346" scaleY="0.5" />
    <Platform type="Platform" material="" x="-0.449" y="0.5698" rotation="90.0" scaleX="3.1031" scaleY="0.5" />
    <Platform type="Platform" material="" x="-1.465" y="1.3997" rotation="0.0" scaleX="3.5953" scaleY="0.5" />
    <ExternalAgent type="novel_object_38_1_1" material="" x="-11.319" y="-0.9602" rotation="0.0" scaleX="1.0" scaleY="1.0" />
    <Block type="RectSmall" material="ice" x="-8.5745" y="-3.39" rotation="0" />
    <Block type="RectSmall" material="stone" x="-2.271" y="-3.39" rotation="0" />
    <Block type="SquareSmall" material="ice" x="8.7248" y="-3.285" rotation="0" />
    <Block type="SquareHole" material="wood" x="4.7711" y="-3.08" rotation="0" />
    <Block type="RectSmall" material="stone" x="-3.9142" y="-3.39" rotation="0" />
  </GameObjects>
</Level>
