<?xml version="1.0" encoding="utf-16"?>
<Level width="2">
  <Camera x="0" y="-1" minWidth="25" maxWidth="35" />
  <Score highScore="0" />
  <Birds>
    <Bird type="BirdRed"/>
    <Bird type="BirdRed"/>
  </Birds>
  <Slingshot x="-12.0" y="-2.5" />
  <GameObjects>
    <Pig type="BasicSmall" material="" x="-0.5612" y="0.9916" rotation="0.3056" />
    <Platform type="Platform" material="" x="-1.5118" y="0.6084" rotation="0.0" scaleX="4.7346" scaleY="0.5" />
    <Platform type="Platform" material="" x="-0.1587" y="1.4585" rotation="90.0" scaleX="3.1031" scaleY="0.5" />
    <Platform type="Platform" material="" x="-2.0057" y="2.2884" rotation="0.0" scaleX="1.0" scaleY="0.5" />
    <Platform type="Platform" material="" x="-1.8587" y="1.2985" rotation="90.0" scaleX="2.5976" scaleY="0.5" />
    <Block type="SquareSmall" material="ice" x="0.2356" y="-3.285" rotation="0" />
    <Block type="SquareTiny" material="ice" x="-4.0588" y="-3.39" rotation="0" />
  </GameObjects>
</Level>
