<?xml version="1.0" encoding="utf-16"?>
<Level width="2">
  <Camera x="0" y="-1" minWidth="25" maxWidth="35" />
  <Score highScore="0" />
  <Birds>
    <Bird type="BirdRed"/>
  </Birds>
  <Slingshot x="-12.0" y="-2.5" />
  <GameObjects>
    <Pig type="BasicSmall" material="" x="-6.9594" y="-0.6567" rotation="0.5998" />
    <Platform type="Platform" material="" x="-7.4623" y="-1.0381" rotation="0.0" scaleX="4.7346" scaleY="0.5" />
    <Platform type="Platform" material="" x="-6.1092" y="-0.188" rotation="90.0" scaleX="3.1031" scaleY="0.5" />
    <Platform type="Platform" material="" x="-7.1252" y="0.6419" rotation="0.0" scaleX="3.5953" scaleY="0.5" />
    <ExternalAgent type="novel_object_38_1_1" material="" x="-16.9792" y="-1.718" rotation="0.0" scaleX="1.0" scaleY="1.0" />
    <Block type="Triangle" material="ice" x="-7.4108" y="-3.09" rotation="0" />
    <Block type="CircleSmall" material="ice" x="-9.2449" y="-3.275" rotation="0" />
    <Block type="RectMedium" material="ice" x="0.8879" y="-3.39" rotation="0" />
    <Block type="RectTiny" material="wood" x="4.0091" y="-3.39" rotation="0" />
    <Block type="RectSmall" material="ice" x="-4.908" y="-3.39" rotation="0" />
    <ExternalAgent type="Worm" material="" x="-7.4623" y="-1.0381" rotation="0" />
  </GameObjects>
</Level>
