<?xml version="1.0" encoding="utf-16"?>
<Level width="2">
  <Camera x="0" y="-1" minWidth="25" maxWidth="35" />
  <Score highScore="0" />
  <Birds>
    <Bird type="BirdRed"/>
    <Bird type="BirdRed"/>
  </Birds>
  <Slingshot x="-12.0" y="-2.5" />
  <GameObjects>
    <Pig type="BasicSmall" material="" x="-0.9833" y="0.1466" rotation="0.9321" />
    <Pig type="BasicSmall" material="" x="-2.8586" y="0.1449" rotation="359.6748" />
    <Platform type="Platform" material="" x="-2.4196" y="-0.2391" rotation="0.0" scaleX="6.2566" scaleY="0.5" />
    <Platform type="Platform" material="" x="-4.2706" y="0.2419" rotation="90.0" scaleX="2.0" scaleY="0.5" />
    <Platform type="Platform" material="" x="-0.5796" y="0.2516" rotation="90.0" scaleX="1.979" scaleY="0.5" />
    <Platform type="Platform" material="" x="-2.4566" y="0.3909" rotation="90.0" scaleX="1.5158" scaleY="0.5" />
    <Block type="Circle" material="ice" x="3.4663" y="-3.1" rotation="0" />
    <Block type="SquareHole" material="stone" x="-6.1592" y="-3.08" rotation="0" />
    <Platform type="Platform" material="" x="-9.3548" y="-3.18" rotation="0" scaleX="1.0" scaleY="1.0" />
    <Platform type="Platform" material="" x="6.6281" y="-3.18" rotation="0" scaleX="1.0" scaleY="1.0" />
    <Block type="RectSmall" material="stone" x="-0.0716" y="-3.39" rotation="0" />
    <ExternalAgent type="Magician" material="" x="-2.5003" y="-2.8293" rotation="0" />
  </GameObjects>
</Level>
