<?xml version="1.0" encoding="utf-16"?>
<Level width="2">
  <Camera x="0" y="-1" minWidth="25" maxWidth="35" />
  <Score highScore="0" />
  <Birds>
    <Bird type="BirdRed"/>
  </Birds>
  <Slingshot x="-12.0" y="-2.5" />
  <GameObjects>
    <Pig type="BasicSmall" material="" x="-4.1974" y="0.2499" rotation="0.5998" />
    <Platform type="Platform" material="" x="-4.7004" y="-0.1315" rotation="0.0" scaleX="4.7346" scaleY="0.5" />
    <Platform type="Platform" material="" x="-3.3472" y="0.7186" rotation="90.0" scaleX="3.1031" scaleY="0.5" />
    <Platform type="Platform" material="" x="-4.3632" y="1.5485" rotation="0.0" scaleX="3.5953" scaleY="0.5" />
    <Block type="SquareTiny" material="wood" x="-4.1808" y="-3.39" rotation="0" />
    <Block type="SquareHole" material="wood" x="8.8329" y="-3.08" rotation="0" />
    <Block type="SquareSmall" material="stone" x="1.1271" y="-3.285" rotation="0" />
    <Block type="CircleSmall" material="wood" x="5.701" y="-3.275" rotation="0" />
    <ExternalAgent type="Worm" material="" x="-4.7004" y="-0.1315" rotation="0" />
  </GameObjects>
</Level>
