<?xml version="1.0" encoding="utf-16"?>
<Level width="2">
  <Camera x="0" y="-1" minWidth="25" maxWidth="35" />
  <Score highScore="0" />
  <Birds>
    <Bird type="BirdRed"/>
  </Birds>
  <Slingshot x="-12.0" y="-2.5" />
  <GameObjects>
    <Pig type="BasicSmall" material="" x="-0.1866" y="0.9604" rotation="0.5998" />
    <Platform type="Platform" material="" x="-0.6895" y="0.579" rotation="0.0" scaleX="4.7346" scaleY="0.5" />
    <Platform type="Platform" material="" x="0.6636" y="1.4291" rotation="90.0" scaleX="3.1031" scaleY="0.5" />
    <Platform type="Platform" material="" x="-0.3524" y="2.259" rotation="0.0" scaleX="3.5953" scaleY="0.5" />
    <Block type="RectBig" material="ice" x="8.6429" y="-3.39" rotation="0" />
    <Block type="SquareTiny" material="ice" x="5.1256" y="-3.39" rotation="0" />
    <Block type="SquareHole" material="ice" x="-0.1675" y="-3.08" rotation="0" />
    <Block type="RectFat" material="ice" x="-6.3791" y="-3.285" rotation="0" />
    <ExternalAgent type="Worm" material="" x="-0.6895" y="0.579" rotation="0" />
  </GameObjects>
</Level>
