<?xml version="1.0" encoding="utf-16"?>
<Level width="2">
  <Camera x="0" y="-1" minWidth="25" maxWidth="35" />
  <Score highScore="0" />
  <Birds>
    <Bird type="BirdRed"/>
    <Bird type="BirdRed"/>
  </Birds>
  <Slingshot x="-12.0" y="-2.5" />
  <GameObjects>
    <Pig type="BasicSmall" material="" x="-3.5574" y="-0.5383" rotation="0.9321" />
    <Pig type="BasicSmall" material="" x="-5.4327" y="-0.54" rotation="359.6748" />
    <Platform type="Platform" material="" x="-4.9938" y="-0.924" rotation="0.0" scaleX="6.2566" scaleY="0.5" />
    <Platform type="Platform" material="" x="-6.8448" y="-0.443" rotation="90.0" scaleX="2.0" scaleY="0.5" />
    <Platform type="Platform" material="" x="-3.1538" y="-0.4333" rotation="90.0" scaleX="1.979" scaleY="0.5" />
    <Platform type="Platform" material="" x="-5.0308" y="-0.294" rotation="90.0" scaleX="1.5158" scaleY="0.5" />
    <Block type="TriangleHole" material="wood" x="-5.2514" y="-3.09" rotation="0" />
    <Block type="RectMedium" material="wood" x="-9.9519" y="-3.39" rotation="0" />
    <Block type="RectBig" material="ice" x="-1.4793" y="-3.39" rotation="0" />
  </GameObjects>
</Level>
