<?xml version="1.0" encoding="utf-16"?>
<Level width="2">
  <Camera x="0" y="-1" minWidth="25" maxWidth="35" />
  <Score highScore="0" />
  <Birds>
    <Bird type="novel_object_1012"/>
    <Bird type="BirdYellow"/>
  </Birds>
  <Slingshot x="-12.0" y="-2.5" />
  <GameObjects>
    <Pig type="BasicSmall" material="" x="-2.3038" y="-0.063" rotation="1.2754" />
    <Pig type="BasicSmall" material="" x="-4.1827" y="-0.0632" rotation="359.924" />
    <Pig type="BasicSmall" material="" x="-6.3038" y="-0.063" rotation="1.2754" />
    <Platform type="Platform" material="" x="-3.6386" y="-0.4478" rotation="0.0" scaleX="9.2567" scaleY="0.5" />
    <Platform type="Platform" material="" x="-5.4896" y="0.8332" rotation="90.0" scaleX="4.0" scaleY="0.5" />
    <Platform type="Platform" material="" x="-1.7486" y="0.0428" rotation="90.0" scaleX="1.979" scaleY="0.5" />
    <Platform type="Platform" material="" x="-3.7756" y="-0.1079" rotation="90.0" scaleX="1.0" scaleY="0.5" />
    <Block type="RectMedium" material="ice" x="-3.0945" y="-3.39" rotation="0" />
    <Block type="SquareHole" material="wood" x="-7.8104" y="-3.08" rotation="0" />
    <Block type="RectSmall" material="wood" x="1.0372" y="-3.39" rotation="0" />
    <Block type="CircleSmall" material="ice" x="-5.2529" y="-3.275" rotation="0" />
  </GameObjects>
</Level>
